pumaska/__init__.py
pumaska/koriste.py
pumaska/lomake.py
pumaska/nidottu.py
pumaska/piirto.py
pumaska/sarja.py
pumaska/static/pumaska/js/jquery.formset.js
pumaska/templates/pumaska/lomakesarja.html
pumaska/templates/pumaska/lomakesarja_lomakekenttana.html
pumaska/templates/pumaska/lomakesarja_rivi.html
testit/migrations/0001_initial.py
testit/migrations/__init__.py
django_pumaska-1.4.7.dist-info/METADATA
django_pumaska-1.4.7.dist-info/WHEEL
django_pumaska-1.4.7.dist-info/entry_points.txt
django_pumaska-1.4.7.dist-info/historia.json
django_pumaska-1.4.7.dist-info/top_level.txt
django_pumaska-1.4.7.dist-info/RECORD
