Metadata-Version: 2.1
Name: django-pumaska
Version: 1.4.7
Summary: Sisäkkäisten lomakkeiden ja -sarjojen käsittely
Author-email: Antti Hautaniemi <antti.hautaniemi@pispalanit.fi>
Project-URL: Repository, https://github.com/an7oine/django-pumaska.git
Requires-Python: >=3.8
